olsq/__init__.py
olsq/device.py
olsq/display.py
olsq/input.py
olsq/output.py
olsq/solve.py
olsq/benchmarks/4gt13_92.qasm
olsq/benchmarks/4mod5-v1_22.qasm
olsq/benchmarks/adder.qasm
olsq/benchmarks/barenco_tof_4.qasm
olsq/benchmarks/barenco_tof_5.qasm
olsq/benchmarks/mod5mils_65.qasm
olsq/benchmarks/mod_mult_55.qasm
olsq/benchmarks/or.qasm
olsq/benchmarks/qaoa5.qasm
olsq/benchmarks/queko_05_0.qasm
olsq/benchmarks/queko_10_3.qasm
olsq/benchmarks/queko_15_1.qasm
olsq/benchmarks/rc_adder_6.qasm
olsq/benchmarks/tof_4.qasm
olsq/benchmarks/tof_5.qasm
olsq/benchmarks/toffoli.qasm
olsq/benchmarks/vbe_adder_3.qasm
olsq/devices/default_1a.json
olsq/devices/default_1b.json
olsq/devices/default_2a.json
olsq/devices/default_2b.json
olsq/devices/default_3a.json
olsq/devices/default_3b.json
olsq/devices/default_aspen4.json
olsq/devices/default_grid2by3.json
olsq/devices/default_grid2by4.json
olsq/devices/default_ibmqx2.json
olsq/devices/default_melbourne.json
olsq/devices/default_ourense.json
olsq/devices/default_sycamore23.json
olsq/devices/default_tokyo.json
olsq/olsq_cirq/__init__.py
olsq/olsq_cirq/input.py
olsq/olsq_cirq/output.py
olsq/olsq_cirq/solve.py
olsq/olsq_qiskit/__init__.py
olsq/olsq_qiskit/input.py
olsq/olsq_qiskit/output.py
olsq/olsq_qiskit/solve.py
olsq_cirq/__init__.py
olsq_cirq/input.py
olsq_cirq/output.py
olsq_cirq/solve.py
olsq_qiskit/__init__.py
olsq_qiskit/input.py
olsq_qiskit/output.py
olsq_qiskit/solve.py
olsq-0.0.4.dist-info/LICENSE
olsq-0.0.4.dist-info/METADATA
olsq-0.0.4.dist-info/WHEEL
olsq-0.0.4.dist-info/top_level.txt
olsq-0.0.4.dist-info/RECORD
