Metadata-Version: 2.1
Name: olsq
Version: 0.0.4
Summary: Optimal Layout Synthesis for Quantum Computing (OLSQ) for mapping and scheduling quantum circuits
Home-page: https://github.com/tbcdebug/OLSQ
Author: Daniel Bochen Tan
Author-email: bctan@cs.ucla.edu
License: BSD
Project-URL: Bug Tracker, https://github.com/tbcdebug/OLSQ/issues
Platform: UNKNOWN
Classifier: Programming Language :: Python :: 3
Classifier: License :: OSI Approved :: BSD License
Classifier: Operating System :: OS Independent
Requires-Python: >=3.6
Requires-Dist: networkx (>=2.5)
Requires-Dist: z3-solver (>=4.8.9.0)
